open_meteo_mcp/__init__.py
open_meteo_mcp/__main__.py
open_meteo_mcp/server.py
open_meteo_mcp/utils.py
open_meteo_mcp/tools/__init__.py
open_meteo_mcp/tools/air_quality_service.py
open_meteo_mcp/tools/toolhandler.py
open_meteo_mcp/tools/tools_air_quality.py
open_meteo_mcp/tools/tools_time.py
open_meteo_mcp/tools/tools_weather.py
open_meteo_mcp/tools/weather_service.py
open_meteo_mcp-0.1.1.dist-info/licenses/LICENSE
open_meteo_mcp-0.1.1.dist-info/METADATA
open_meteo_mcp-0.1.1.dist-info/WHEEL
open_meteo_mcp-0.1.1.dist-info/entry_points.txt
open_meteo_mcp-0.1.1.dist-info/top_level.txt
open_meteo_mcp-0.1.1.dist-info/RECORD
